pbx_component_files_uploader/__init__.py
pbx_component_files_uploader/exceptions/errors.py
pbx_component_files_uploader/ext/selectel/auth.py
pbx_component_files_uploader/ext/selectel/selectel.py
pbx_component_files_uploader/ext/selectel/token.py
pbx_component_files_uploader/interfaces/base_uploader.py
pbx_component_files_uploader/uploader.py
pbx_component_files_uploader-0.0.4.dist-info/LICENSE
pbx_component_files_uploader-0.0.4.dist-info/METADATA
pbx_component_files_uploader-0.0.4.dist-info/WHEEL
pbx_component_files_uploader-0.0.4.dist-info/RECORD
