Metadata-Version: 2.1
Name: pbx-component-files-uploader
Version: 0.0.4
Summary: Files uploader to custom storages
Home-page: https://github.com/leadvertex/pbx-component-files-uploader
License: MIT
Keywords: leadvertex,selectel,storage,remote storage,uploader
Author: Ivan Kalashnikov
Author-email: ivan@leadvertex.ru
Requires-Python: >=3.7,<4.0
Classifier: License :: OSI Approved :: MIT License
Classifier: Programming Language :: Python :: 3
Classifier: Programming Language :: Python :: 3.7
Classifier: Programming Language :: Python :: 3.8
Classifier: Programming Language :: Python :: 3.9
Classifier: Programming Language :: Python :: 3.10
Classifier: Programming Language :: Python :: 3.11
Requires-Dist: requests (==2.27.1)
Project-URL: Repository, https://github.com/leadvertex/pbx-component-files-uploader
